nautobot_ssot/__init__.py
nautobot_ssot/api/__init__.py
nautobot_ssot/api/serializers.py
nautobot_ssot/api/urls.py
nautobot_ssot/api/views.py
nautobot_ssot/app-config-schema.json
nautobot_ssot/choices.py
nautobot_ssot/contrib/__init__.py
nautobot_ssot/contrib/adapter.py
nautobot_ssot/contrib/base.py
nautobot_ssot/contrib/model.py
nautobot_ssot/contrib/sorting.py
nautobot_ssot/contrib/typeddicts.py
nautobot_ssot/contrib/types.py
nautobot_ssot/exceptions.py
nautobot_ssot/filters.py
nautobot_ssot/forms.py
nautobot_ssot/integrations/__init__.py
nautobot_ssot/integrations/aci/__init__.py
nautobot_ssot/integrations/aci/constant.py
nautobot_ssot/integrations/aci/diffsync/__init__.py
nautobot_ssot/integrations/aci/diffsync/adapters/__init__.py
nautobot_ssot/integrations/aci/diffsync/adapters/aci.py
nautobot_ssot/integrations/aci/diffsync/adapters/nautobot.py
nautobot_ssot/integrations/aci/diffsync/client.py
nautobot_ssot/integrations/aci/diffsync/device-types/APIC-SERVER-L2.yaml
nautobot_ssot/integrations/aci/diffsync/device-types/APIC-SERVER-L3.yaml
nautobot_ssot/integrations/aci/diffsync/device-types/APIC-SERVER-M1.yaml
nautobot_ssot/integrations/aci/diffsync/device-types/APIC-SERVER-M3.yaml
nautobot_ssot/integrations/aci/diffsync/device-types/APIC-SIM.yaml
nautobot_ssot/integrations/aci/diffsync/device-types/N2K-C2232PP-10GE.yaml
nautobot_ssot/integrations/aci/diffsync/device-types/N2K-C2232TM-10GE.yaml
nautobot_ssot/integrations/aci/diffsync/device-types/N2K-C2232TM-E-10GE.yaml
nautobot_ssot/integrations/aci/diffsync/device-types/N2K-C2248PQ-10GE.yaml
nautobot_ssot/integrations/aci/diffsync/device-types/N2K-C2248TP-1GE.yaml
nautobot_ssot/integrations/aci/diffsync/device-types/N2K-C2248TP-E-1GE.yaml
nautobot_ssot/integrations/aci/diffsync/device-types/N2K-C2348TQ-10GE.yaml
nautobot_ssot/integrations/aci/diffsync/device-types/N2K-C2348UPQ-10GE.yaml
nautobot_ssot/integrations/aci/diffsync/device-types/N9K-C93108LC-EX.yaml
nautobot_ssot-3.10.0.dist-info/LICENSE
nautobot_ssot-3.10.0.dist-info/METADATA
nautobot_ssot-3.10.0.dist-info/WHEEL
nautobot_ssot-3.10.0.dist-info/entry_points.txt
nautobot_ssot-3.10.0.dist-info/RECORD
