Metadata-Version: 2.3
Name: nautobot-ssot
Version: 3.10.0
Summary: Nautobot Single Source of Truth
License: Apache-2.0
Keywords: nautobot,nautobot-app,nautobot-plugin
Author: Network to Code, LLC
Author-email: opensource@networktocode.com
Requires-Python: >=3.10,<3.13
Classifier: Development Status :: 5 - Production/Stable
Classifier: Intended Audience :: Developers
Classifier: License :: OSI Approved :: Apache Software License
Classifier: Programming Language :: Python :: 3
Classifier: Programming Language :: Python :: 3.10
Classifier: Programming Language :: Python :: 3.11
Classifier: Programming Language :: Python :: 3.12
Provides-Extra: aci
Provides-Extra: all
Provides-Extra: aristacv
Provides-Extra: bootstrap
Provides-Extra: citrix-adm
Provides-Extra: device42
Provides-Extra: dna-center
Provides-Extra: infoblox
Provides-Extra: ipfabric
Provides-Extra: meraki
Provides-Extra: nautobot-device-lifecycle-mgmt
Provides-Extra: pysnow
Provides-Extra: servicenow
Provides-Extra: slurpit
Requires-Dist: Jinja2 (>=2.11.3) ; extra == "all" or extra == "servicenow"
Requires-Dist: Markdown (!=3.3.5)
Requires-Dist: PyYAML (>=6) ; extra == "aci" or extra == "all" or extra == "servicenow"
Requires-Dist: cloudvision (>=1.9.0,<2.0.0) ; extra == "all" or extra == "aristacv"
Requires-Dist: cvprac (>=1.2.2,<2.0.0) ; extra == "all" or extra == "aristacv"
Requires-Dist: diffsync (>=2.0.0,<3.0.0)
Requires-Dist: dnacentersdk (>=2.5.6,<3.0.0) ; extra == "all" or extra == "dna-center"
Requires-Dist: dnspython (>=2.1.0,<3.0.0) ; extra == "all" or extra == "infoblox"
Requires-Dist: httpx (>=0.23.3) ; extra == "ipfabric"
Requires-Dist: ijson (>=2.5.1) ; extra == "all" or extra == "pysnow" or extra == "servicenow"
Requires-Dist: ipfabric (>=7.3.1,<8.0.0) ; extra == "all" or extra == "ipfabric"
Requires-Dist: meraki (>=1.37.2,<1.46.0) ; extra == "all" or extra == "meraki"
Requires-Dist: nautobot (>=2.4.20,<3.0.0)
Requires-Dist: nautobot-device-lifecycle-mgmt (>=2.0.0) ; extra == "all" or extra == "nautobot-device-lifecycle-mgmt"
Requires-Dist: netutils (>=1.9.0,<2.0.0) ; extra == "all" or extra == "citrix-adm" or extra == "dna-center" or extra == "ipfabric"
Requires-Dist: oauthlib (>=3.1.0) ; extra == "all" or extra == "pysnow" or extra == "servicenow"
Requires-Dist: packaging (>=21.3)
Requires-Dist: prometheus-client (>=0.17.1)
Requires-Dist: python-magic (>=0.4.15) ; extra == "all" or extra == "pysnow" or extra == "servicenow"
Requires-Dist: pytz (>=2019.3) ; extra == "all" or extra == "bootstrap" or extra == "pysnow" or extra == "servicenow"
Requires-Dist: requests (>=2.21.0) ; extra == "all" or extra == "citrix-adm" or extra == "device42" or extra == "pysnow" or extra == "servicenow"
Requires-Dist: requests-oauthlib (>=1.3.0) ; extra == "all" or extra == "pysnow" or extra == "servicenow"
Requires-Dist: six (>=1.13.0) ; extra == "all" or extra == "pysnow" or extra == "servicenow"
Requires-Dist: slurpit-sdk (==0.9.93) ; extra == "all" or extra == "slurpit"
Requires-Dist: urllib3 (>=2.2.3) ; extra == "all" or extra == "citrix-adm"
Project-URL: Documentation, https://docs.nautobot.com/projects/ssot/en/latest/
Project-URL: Homepage, https://github.com/nautobot/nautobot-app-ssot
Project-URL: Repository, https://github.com/nautobot/nautobot-app-ssot
